odoo/addons/l10n_jp_partner_zip_address/README.rst
odoo/addons/l10n_jp_partner_zip_address/__init__.py
odoo/addons/l10n_jp_partner_zip_address/__manifest__.py
odoo/addons/l10n_jp_partner_zip_address/i18n/ja.po
odoo/addons/l10n_jp_partner_zip_address/i18n/l10n_jp_partner_zip_address.pot
odoo/addons/l10n_jp_partner_zip_address/models/__init__.py
odoo/addons/l10n_jp_partner_zip_address/models/res_partner.py
odoo/addons/l10n_jp_partner_zip_address/models/zip_search_mixin.py
odoo/addons/l10n_jp_partner_zip_address/readme/DESCRIPTION.md
odoo/addons/l10n_jp_partner_zip_address/static/description/icon.png
odoo/addons/l10n_jp_partner_zip_address/static/description/index.html
odoo/addons/l10n_jp_partner_zip_address/tests/__init__.py
odoo/addons/l10n_jp_partner_zip_address/tests/test_jp_partner_zip_address.py
odoo_addon_l10n_jp_partner_zip_address-18.0.1.0.1.dist-info/METADATA
odoo_addon_l10n_jp_partner_zip_address-18.0.1.0.1.dist-info/WHEEL
odoo_addon_l10n_jp_partner_zip_address-18.0.1.0.1.dist-info/top_level.txt
odoo_addon_l10n_jp_partner_zip_address-18.0.1.0.1.dist-info/RECORD
