Metadata-Version: 2.1
Name: odoo-addon-l10n_jp_partner_zip_address
Version: 18.0.1.0.1
Requires-Python: >=3.10
Requires-Dist: jaconv
Requires-Dist: odoo==18.0.*
Summary: Japan Partner Zip Address
Home-page: https://github.com/OCA/l10n-japan
License: AGPL-3
Author: Quartile, Odoo Community Association (OCA)
Author-email: support@odoo-community.org
Classifier: Programming Language :: Python
Classifier: Framework :: Odoo
Classifier: Framework :: Odoo :: 18.0
Classifier: License :: OSI Approved :: GNU Affero General Public License v3
